setup.py
zooz/__init__.py
zooz/client.py
zooz/exceptions.py
zooz/utils.py
zooz_python.egg-info/PKG-INFO
zooz_python.egg-info/SOURCES.txt
zooz_python.egg-info/dependency_links.txt
zooz_python.egg-info/requires.txt
zooz_python.egg-info/top_level.txt