Metadata-Version: 1.0
Name: zooz-python
Version: 0.4
Summary: Python client for ZooZ payments API
Home-page: https://github.com/jneight/zooz-python
Author: Javier Cordero Martinez
Author-email: jcorderomartinez@gmail.com
License: Apache 2.0
Platform: UNKNOWN
